pybibget/__init__.py
pybibget/bibentry.py
pybibget/tests/test_bibget.py
pybibget-0.2.0.dist-info/licenses/LICENSE
pybibget-0.2.0.dist-info/METADATA
pybibget-0.2.0.dist-info/WHEEL
pybibget-0.2.0.dist-info/entry_points.txt
pybibget-0.2.0.dist-info/top_level.txt
pybibget-0.2.0.dist-info/RECORD
