Metadata-Version: 2.4
Name: pybibget
Version: 0.2.0
Summary: Command line utility to automatically retrieve BibTeX citations from MathSciNet, arXiv, PubMed and doi.org
Author-email: Dominik Schröder <schroeder.dominik@gmail.com>
License: MIT License
Project-URL: Homepage, https://github.com/wirhabenzeit/pybibget
Keywords: BibTeX,MathSciNet,PubMed,DOI,arXiv,bibliography,command-line,citation
Classifier: Programming Language :: Python :: 3
Classifier: License :: OSI Approved :: MIT License
Classifier: Operating System :: OS Independent
Requires-Python: >=3.8
License-File: LICENSE
Requires-Dist: pybtex>=0.24.0
Requires-Dist: lxml>=4.9.2
Requires-Dist: pylatexenc>=1.3
Requires-Dist: aiolimiter>=1.0.0
Requires-Dist: appdirs>=1.0.0
Requires-Dist: httpx>=0.21.0
Requires-Dist: typer>=0.20.1
Dynamic: license-file
